fecloudsdkkms/__init__.py
fecloudsdkkms/v2/__init__.py
fecloudsdkkms/v2/kms_async_client.py
fecloudsdkkms/v2/kms_client.py
fecloudsdkkms/v2/model/__init__.py
fecloudsdkkms/v2/model/action_resources.py
fecloudsdkkms/v2/model/api_link.py
fecloudsdkkms/v2/model/api_version_detail.py
fecloudsdkkms/v2/model/batch_create_kms_tags_request.py
fecloudsdkkms/v2/model/batch_create_kms_tags_request_body.py
fecloudsdkkms/v2/model/batch_create_kms_tags_response.py
fecloudsdkkms/v2/model/cancel_grant_request.py
fecloudsdkkms/v2/model/cancel_grant_response.py
fecloudsdkkms/v2/model/cancel_key_deletion_request.py
fecloudsdkkms/v2/model/cancel_key_deletion_response.py
fecloudsdkkms/v2/model/cancel_self_grant_request.py
fecloudsdkkms/v2/model/cancel_self_grant_response.py
fecloudsdkkms/v2/model/create_datakey_request.py
fecloudsdkkms/v2/model/create_datakey_request_body.py
fecloudsdkkms/v2/model/create_datakey_response.py
fecloudsdkkms/v2/model/create_datakey_without_plaintext_request.py
fecloudsdkkms/v2/model/create_datakey_without_plaintext_response.py
fecloudsdkkms/v2/model/create_grant_request.py
fecloudsdkkms/v2/model/create_grant_request_body.py
fecloudsdkkms/v2/model/create_grant_response.py
fecloudsdkkms/v2/model/create_key_request.py
fecloudsdkkms/v2/model/create_key_request_body.py
fecloudsdkkms/v2/model/create_key_response.py
fecloudsdkkms/v2/model/create_key_store_request.py
fecloudsdkkms/v2/model/create_key_store_request_body.py
fecloudsdkkms/v2/model/create_key_store_response.py
fecloudsdkkms/v2/model/create_kms_tag_request.py
fecloudsdkkms/v2/model/create_kms_tag_request_body.py
fecloudsdkkms/v2/model/create_kms_tag_response.py
fecloudsdkkms/v2/model/create_parameters_for_import_request.py
fecloudsdkkms/v2/model/create_parameters_for_import_response.py
fecloudsdkkms/v2/model/create_random_request.py
fecloudsdkkms/v2/model/create_random_response.py
fecloudsdkkms/v2/model/decrypt_data_request.py
fecloudsdkkms/v2/model/decrypt_data_request_body.py
fecloudsdkkms-0.0.1b0.dist-info/LICENSE
fecloudsdkkms-0.0.1b0.dist-info/METADATA
fecloudsdkkms-0.0.1b0.dist-info/WHEEL
fecloudsdkkms-0.0.1b0.dist-info/top_level.txt
fecloudsdkkms-0.0.1b0.dist-info/RECORD
