Metadata-Version: 2.1
Name: fecloudsdkkms
Version: 0.0.1b0
Summary: KMS
Home-page: https://github.com/fecloud/fecloud-sdk-python-v3
Author: FeCloud SDK
Author-email: fecloud.fe@gmail.com
License: Apache LICENSE 2.0
Keywords: fecloud,sdk,KMS
Classifier: Development Status :: 5 - Production/Stable
Classifier: Intended Audience :: Developers
Classifier: License :: OSI Approved :: Apache Software License
Classifier: Programming Language :: Python :: 2.7
Classifier: Programming Language :: Python :: 3.3
Classifier: Programming Language :: Python :: 3.4
Classifier: Programming Language :: Python :: 3.5
Classifier: Programming Language :: Python :: 3.6
Classifier: Programming Language :: Python :: 3.7
Classifier: Programming Language :: Python :: 3.8
Classifier: Programming Language :: Python :: 3.9
Classifier: Topic :: Software Development
Requires-Python: >=2.7,!=3.0.*,!=3.1.*,!=3.2.*
License-File: LICENSE
Requires-Dist: fecloudsdkcore >=0.0.1-beta
